landscapelaser
