Metadata-Version: 2.1
Name: landscapelaser
Version: 0.1.1
Summary: A library to calculate sharpness value of loss-landscapes
Author: Saksham Bassi
License: MIT License
Keywords: loss-landscapes,sharpness,nlp,machinelearning
Classifier: Intended Audience :: Developers
Classifier: Intended Audience :: Science/Research
Classifier: License :: OSI Approved :: MIT License
Classifier: Topic :: Scientific/Engineering :: Artificial Intelligence
Classifier: Programming Language :: Python :: 3
License-File: LICENSE
